test_de_toolkit/__init__.py
test_de_toolkit/main.py
test_de_toolkit/vm.py
test_de_toolkit-0.1.0.dist-info/METADATA
test_de_toolkit-0.1.0.dist-info/WHEEL
test_de_toolkit-0.1.0.dist-info/RECORD
